tartiflette_aiohttp/__init__.py
tartiflette_aiohttp-0.1.0.dist-info/LICENSE
tartiflette_aiohttp-0.1.0.dist-info/METADATA
tartiflette_aiohttp-0.1.0.dist-info/WHEEL
tartiflette_aiohttp-0.1.0.dist-info/top_level.txt
tartiflette_aiohttp-0.1.0.dist-info/RECORD
