Metadata-Version: 2.1
Name: tartiflette-aiohttp
Version: 0.1.0
Summary: Runs a Tartiflette GraphQL Engine through aiohttp
Home-page: https://github.com/dailymotion/tartiflette-aiohttp
Author: Dailymotion Core API Team
Author-email: team@tartiflette.io
License: MIT
Keywords: api graphql protocol api rest relay tartiflette dailymotion
Platform: UNKNOWN
Classifier: Intended Audience :: Developers
Classifier: Topic :: Software Development :: Libraries
Classifier: Programming Language :: Python :: 3.6
Classifier: Programming Language :: Python :: Implementation :: PyPy
Requires-Dist: aiohttp (~=3.4)
Requires-Dist: tartiflette (~=0.1)
Provides-Extra: test
Requires-Dist: pytest; extra == 'test'
Requires-Dist: pytest-benchmark; extra == 'test'
Requires-Dist: pytest-cov; extra == 'test'
Requires-Dist: pytest-asyncio; extra == 'test'
Requires-Dist: pytz; extra == 'test'
Requires-Dist: pylint (==2.1.1); extra == 'test'
Requires-Dist: xenon; extra == 'test'
Requires-Dist: black (==18.9b0); extra == 'test'
